laserlib/__init__.py
laserlib/laser.py
laserlib-0.1.dist-info/LICENSE
laserlib-0.1.dist-info/METADATA
laserlib-0.1.dist-info/WHEEL
laserlib-0.1.dist-info/top_level.txt
laserlib-0.1.dist-info/RECORD
