Metadata-Version: 2.1
Name: laserlib
Version: 0.1
Summary: A library for communication with laser model produced by Micro photons(Shanghai)Technology Co., Ltd.
Home-page: https://github.com/JackyZhang26/laserlib
Author: Jacky Zhang
Author-email: jackyzhang26@outlook.com
License: MIT
License-File: LICENSE
Requires-Dist: pyserial
